[
  {"排名": "1", "院校代码": "10001", "院校名称": "北京大学", "录取人数": "2", "最低分": "693", "最低排位": "2"},
  {"排名": "2", "院校代码": "10003", "院校名称": "清华大学", "录取人数": "3", "最低分": "683", "最低排位": "8"},
  {"排名": "3", "院校代码": "10246", "院校名称": "复旦大学", "录取人数": "8", "最低分": "675", "最低排位": "21"},
  {"排名": "4", "院校代码": "10358", "院校名称": "中国科学技术大学", "录取人数": "2", "最低分": "675", "最低排位": "26"},
  {"排名": "5", "院校代码": "10248", "院校名称": "上海交通大学", "录取人数": "17", "最低分": "671", "最低排位": "35"},
  {"排名": "6", "院校代码": "10335", "院校名称": "浙江大学", "录取人数": "4", "最低分": "668", "最低排位": "42"},
  {"排名": "7", "院校代码": "19001", "院校名称": "北京大学医学部", "录取人数": "5", "最低分": "667", "最低排位": "44"},
  {"排名": "8", "院校代码": "10002", "院校名称": "中国人民大学", "录取人数": "4", "最低分": "666", "最低排位": "48"},
  {"排名": "9", "院校代码": "10247", "院校名称": "同济大学", "录取人数": "13", "最低分": "658", "最低排位": "74"},
  {"排名": "10", "院校代码": "10272", "院校名称": "上海财经大学", "录取人数": "10", "最低分": "646", "最低排位": "123"},
  {"排名": "11", "院校代码": "10006", "院校名称": "北京航空航天大学", "录取人数": "8", "最低分": "645", "最低排位": "131"},
  {"排名": "12", "院校代码": "10284", "院校名称": "南京大学", "录取人数": "24", "最低分": "639", "最低排位": "149"},
  {"排名": "13", "院校代码": "10027", "院校名称": "北京师范大学", "录取人数": "6", "最低分": "638", "最低排位": "152"},
  {"排名": "14", "院校代码": "10036", "院校名称": "对外经济贸易大学", "录取人数": "3", "最低分": "631", "最低排位": "182"},
  {"排名": "15", "院校代码": "14430", "院校名称": "中国科学院大学", "录取人数": "4", "最低分": "629", "最低排位": "198"},
  {"排名": "16", "院校代码": "10269", "院校名称": "华东师范大学", "录取人数": "8", "最低分": "618", "最低排位": "249"},
  {"排名": "17", "院校代码": "10271", "院校名称": "上海外国语大学", "录取人数": "2", "最低分": "600", "最低排位": "348"},
  {"排名": "18", "院校代码": "10487", "院校名称": "华中科技大学", "录取人数": "40", "最低分": "588", "最低排位": "407"},
  {"排名": "19", "院校代码": "10486", "院校名称": "武汉大学", "录取人数": "56", "最低分": "586", "最低排位": "418"},
  {"排名": "20", "院校代码": "10034", "院校名称": "中央财经大学", "录取人数": "12", "最低分": "578", "最低排位": "460"},
  {"排名": "21", "院校代码": "10698", "院校名称": "西安交通大学", "录取人数": "14", "最低分": "574", "最低排位": "483"},
  {"排名": "22", "院校代码": "10561", "院校名称": "华南理工大学", "录取人数": "14", "最低分": "574", "最低排位": "484"},
  {"排名": "23", "院校代码": "10033", "院校名称": "中国传媒大学", "录取人数": "2", "最低分": "566", "最低排位": "532"},
  {"排名": "24", "院校代码": "10384", "院校名称": "厦门大学", "录取人数": "60", "最低分": "558", "最低排位": "559"},
  {"排名": "25", "院校代码": "10056", "院校名称": "天津大学", "录取人数": "8", "最低分": "555", "最低排位": "571"},
  {"排名": "26", "院校代码": "10610", "院校名称": "四川大学", "录取人数": "30", "最低分": "552", "最低排位": "589"},
  {"排名": "27", "院校代码": "10558", "院校名称": "中山大学", "录取人数": "145", "最低分": "550", "最低排位": "603"},
  {"排名": "28", "院校代码": "10007", "院校名称": "北京理工大学", "录取人数": "8", "最低分": "549", "最低排位": "604"},
  {"排名": "29", "院校代码": "10055", "院校名称": "南开大学", "录取人数": "5", "最低分": "545", "最低排位": "627"},
  {"排名": "30", "院校代码": "10286", "院校名称": "东南大学", "录取人数": "27", "最低分": "543", "最低排位": "639"},
  {"排名": "31", "院校代码": "10030", "院校名称": "北京外国语大学", "录取人数": "1", "最低分": "543", "最低排位": "641"},
  {"排名": "32", "院校代码": "10614", "院校名称": "电子科技大学", "录取人数": "18", "最低分": "531", "最低排位": "695"},
  {"排名": "33", "院校代码": "10013", "院校名称": "北京邮电大学", "录取人数": "10", "最低分": "530", "最低排位": "699"},
  {"排名": "34", "院校代码": "10533", "院校名称": "中南大学", "录取人数": "39", "最低分": "528", "最低排位": "712"},
  {"排名": "35", "院校代码": "10213", "院校名称": "哈尔滨工业大学", "录取人数": "15", "最低分": "520", "最低排位": "59"},
  {"排名": "36", "院校代码": "10532", "院校名称": "湖南大学", "录取人数": "13", "最低分": "520", "最低排位": "760"},
  {"排名": "37", "院校代码": "10611", "院校名称": "重庆大学", "录取人数": "10", "最低分": "517", "最低排位": "772"},
  {"排名": "38", "院校代码": "10574", "院校名称": "华南师范大学", "录取人数": "10", "最低分": "510", "最低排位": "801"},
  {"排名": "39", "院校代码": "10004", "院校名称": "北京交通大学", "录取人数": "7", "最低分": "510", "最低排位": "803"},
  {"排名": "40", "院校代码": "10053", "院校名称": "中国政法大学", "录取人数": "20", "最低分": "508", "最低排位": "813"},
  {"排名": "41", "院校代码": "10141", "院校名称": "大连理工大学", "录取人数": "9", "最低分": "506", "最低排位": "823"},
  {"排名": "42", "院校代码": "10040", "院校名称": "外交学院", "录取人数": "2", "最低分": "502", "最低排位": "8467"},
  {"排名": "43", "院校代码": "10699", "院校名称": "西北工业大学", "录取人数": "3", "最低分": "499", "最低排位": "858"},
  {"排名": "44", "院校代码": "10280", "院校名称": "上海大学", "录取人数": "6", "最低分": "491", "最低排位": "886"},
  {"排名": "45", "院校代码": "19027", "院校名称": "北京师范大学(珠海校区)", "录取人数": "3", "最低分": "490", "最低排位": "887"},
  {"排名": "46", "院校代码": "10635", "院校名称": "西南大学", "录取人数": "5", "最低分": "490", "最低排位": "890"},
  {"排名": "47", "院校代码": "10008", "院校名称": "北京科技大学", "录取人数": "5", "最低分": "487", "最低排位": "904"},
  {"排名": "48", "院校代码": "10590", "院校名称": "深圳大学", "录取人数": "40", "最低分": "483", "最低排位": "920"},
  {"排名": "49", "院校代码": "10511", "院校名称": "华中师范大学", "录取人数": "10", "最低分": "476", "最低排位": ""},
  {"排名": "50", "院校代码": "10287", "院校名称": "南京航空航天大学", "录取人数": "8", "最低分": "476", "最低排位": "951"}
]
